{"swagger":"2.0","info":{"description":"Swagger API documentation for MyJavaService","version":"2.0","title":"MyJavaServiceService Swagger Documentation","x-WM-SERVICE_TYPE":"JavaService","x-WM-SERVICE_ID":"MyJavaService"},"basePath":"","tags":[{"name":"MyJavaController","x-WM-FULLY_QUALIFIED_NAME":"com.test1.myjavaservice.controller.MyJavaController","x-WM-VERSION":""}],"schemes":["https","http"],"paths":{"/myJava/sampleJavaOperation":{"get":{"tags":["MyJavaController"],"operationId":"sampleJavaOperation","produces":["application/json"],"responses":{"200":{"description":"Success","schema":{"type":"string"}}},"x-WM-OPERATION_UID":"85b566c3-c6f5-4512-b126-d2efa7bd6c92","x-WM-ACCESS_SPECIFIER":"APP_ONLY","x-WM-METHOD_IDENTIFIER":"sampleJavaOperation-0-17"},"x-WM-TAG":"MyJavaController","x-WM-BASE_PATH":"/myJava","x-WM-COMPLETE_PATH":"//myJava/sampleJavaOperation","x-WM-RELATIVE_PATH":"/sampleJavaOperation"}},"definitions":{}}